jupyter_builder/__init__.py
jupyter_builder/base_extension_app.py
jupyter_builder/commands.py
jupyter_builder/core_path.py
jupyter_builder/debug_log_file_mixin.py
jupyter_builder/federated_extensions.py
jupyter_builder/federated_extensions_requirements.py
jupyter_builder/jlpm.py
jupyter_builder/jupyterlab_semver.py
jupyter_builder/main.py
jupyter_builder/yarn.js
jupyter_builder/extension_commands/__init__.py
jupyter_builder/extension_commands/build.py
jupyter_builder/extension_commands/develop.py
jupyter_builder/extension_commands/watch.py
jupyter_builder-0.1.0a3.dist-info/METADATA
jupyter_builder-0.1.0a3.dist-info/WHEEL
jupyter_builder-0.1.0a3.dist-info/entry_points.txt
jupyter_builder-0.1.0a3.dist-info/licenses/LICENSE
jupyter_builder-0.1.0a3.dist-info/RECORD
