Metadata-Version: 2.3
Name: jupyter_builder
Version: 0.1.0a3
Summary: JupyterLab build tools
Project-URL: Homepage, https://jupyter.org
Project-URL: Source, https://github.com/jupyterlab/jupyterlab_builder
Project-URL: Issues, https://github.com/jupyterlab/jupyterlab_builder/issues/new/choose
Project-URL: Gitter, https://gitter.im/jupyterlab/jupyterlab
Project-URL: Pypi, https://pypi.org/project/jupyter-builder
Author-email: Jupyter Development Team <jupyter@googlegroups.com>
License: BSD 3-Clause License
License-File: LICENSE
Keywords: ipython,jupyter
Classifier: Framework :: Jupyter
Classifier: Framework :: Jupyter :: JupyterLab
Classifier: Framework :: Jupyter :: JupyterLab :: 4
Classifier: Intended Audience :: Developers
Classifier: License :: OSI Approved :: BSD License
Classifier: Programming Language :: Python
Classifier: Programming Language :: Python :: 3
Classifier: Programming Language :: Python :: 3.8
Classifier: Programming Language :: Python :: 3.9
Classifier: Programming Language :: Python :: 3.10
Classifier: Programming Language :: Python :: 3.11
Classifier: Programming Language :: Python :: 3.12
Requires-Python: >=3.8
Requires-Dist: traitlets
Provides-Extra: dev
Requires-Dist: build; extra == 'dev'
Requires-Dist: hatch; extra == 'dev'
Requires-Dist: mypy; extra == 'dev'
Requires-Dist: pre-commit; extra == 'dev'
Requires-Dist: ruff==0.5.5; extra == 'dev'
Provides-Extra: test
Requires-Dist: copier<10,>=9.2; extra == 'test'
Requires-Dist: coverage; extra == 'test'
Requires-Dist: jinja2-time; extra == 'test'
Requires-Dist: jupyterlab; extra == 'test'
Requires-Dist: pytest-check-links>=0.7; extra == 'test'
Requires-Dist: pytest-cov; extra == 'test'
Requires-Dist: pytest>=7.0; extra == 'test'
